{
  "posts": [
    {
      "id": 1,
      "title": "first-title",
      "author": "Fred",
      "content": "Eo adducta re per Isauriam, rege Persarum bellis finitimis inligato repellenteque a conlimitiis suis ferocissimas gentes"
    },
    {
      "id": 2,
      "title": "modifié",
      "author": "Fred toujours",
      "content": "bref comme d'hab !"
    },
    {
      "id": 3,
      "title": "Bla",
      "author": "lui"
    },
    {
      "id": 6,
      "title": "test fou",
      "author": "oim la mouche",
      "content": "ajouer un contenu ? c'est possible ?"
    },
    {
      "id": 7,
      "title": "titre",
      "author": "lauteur",
      "content": "test contenu du post etc........"
    }
  ],
  "comments": [
    {
      "id": 1,
      "body": "some comment",
      "postId": 1
    },
    {
      "id": 2,
      "body": "some other comment",
      "postId": 3
    },
    {
      "body": "test de comentaries !",
      "postId": 7,
      "id": 3
    },
    {
      "body": "deuxième comm sur le 1 !",
      "postId": 1,
      "id": 4
    }
  ],
  "profile": {
    "name": "typicode"
  }
}